[{"date_last_updated": "2020-09-10 11:05:16", "id": 34148, "name": "Touki Denshou Angel Eyes", "old_names": []}, {"date_last_updated": "2015-12-15 09:28:38", "id": 34149, "name": "My Girlfriend is the President", "old_names": []}, {"date_last_updated": "2015-10-15 18:45:10", "id": 34150, "name": "Radical Radial", "old_names": []}, {"date_last_updated": "2015-07-18 16:08:08", "id": 34151, "name": "Anteater", "old_names": []}, {"date_last_updated": "2018-03-12 18:20:28", "id": 34152, "name": "Paper Wars: Cannon Fodder!", "old_names": []}, {"date_last_updated": "2020-12-31 11:21:36", "id": 34153, "name": "Naruto Shippuden: Kizuna Drive", "old_names": []}, {"date_last_updated": "2011-02-15 00:04:02", "id": 34154, "name": "Tokyo Bus Guide 2", "old_names": []}, {"date_last_updated": "2016-08-29 10:48:24", "id": 34155, "name": "ATV Wild Ride", "old_names": []}, {"date_last_updated": "2015-09-28 14:32:44", "id": 34156, "name": "Sesame Street: Once Upon a Monster", "old_names": []}, {"date_last_updated": "2013-01-06 19:58:57", "id": 34157, "name": "World of Subways Vol.3: Circle Line", "old_names": []}, {"date_last_updated": "2021-03-30 20:11:13", "id": 34158, "name": "Mizzurna Falls", "old_names": []}, {"date_last_updated": "2013-08-16 10:33:21", "id": 34159, "name": "Septentrion: Out of the Blue", "old_names": []}, {"date_last_updated": "2014-06-08 04:28:16", "id": 34160, "name": "Aconcagua", "old_names": []}, {"date_last_updated": "2013-05-07 09:32:30", "id": 34161, "name": "The Witch of Salzburg: Salzburg no Majo", "old_names": []}, {"date_last_updated": "2011-07-19 11:59:56", "id": 34162, "name": "Quiz Climber", "old_names": []}, {"date_last_updated": "2020-03-08 15:14:57", "id": 34164, "name": "Queen's Crown", "old_names": []}, {"date_last_updated": "2012-06-28 09:04:50", "id": 34165, "name": "Baron Wittard: Nemesis of Ragnarok", "old_names": []}, {"date_last_updated": "2011-05-27 23:25:21", "id": 34166, "name": "Dying for Daylight", "old_names": []}, {"date_last_updated": "2011-02-28 18:53:15", "id": 34167, "name": "Sugar Cube", "old_names": []}, {"date_last_updated": "2011-02-16 11:22:48", "id": 34168, "name": "World Snooker Championship Real 2011", "old_names": []}, {"date_last_updated": "2016-04-12 17:29:25", "id": 34169, "name": "Combat Mission: Battle for Normandy", "old_names": []}, {"date_last_updated": "2011-02-16 15:05:14", "id": 34170, "name": "Maverick", "old_names": []}, {"date_last_updated": "2013-02-15 21:15:32", "id": 34171, "name": "Last Action Hero", "old_names": []}, {"date_last_updated": "2019-08-25 02:11:39", "id": 34172, "name": "Cars 2: The Video Game", "old_names": []}, {"date_last_updated": "2011-02-16 15:23:29", "id": 34173, "name": "Hook", "old_names": []}, {"date_last_updated": "2013-06-30 22:45:26", "id": 34174, "name": "ArmA II: Reinforcements", "old_names": []}, {"date_last_updated": "2011-05-07 16:36:14", "id": 34175, "name": "Total Recall", "old_names": []}, {"date_last_updated": "2013-06-23 21:03:05", "id": 34176, "name": "Batman", "old_names": []}, {"date_last_updated": "2011-02-16 17:37:35", "id": 34177, "name": "Checkpoint", "old_names": []}, {"date_last_updated": "2011-02-16 18:54:43", "id": 34178, "name": "Class of 1812", "old_names": []}, {"date_last_updated": "2011-02-16 19:11:04", "id": 34179, "name": "Defender", "old_names": []}, {"date_last_updated": "2011-07-05 16:37:53", "id": 34180, "name": "Kingdom Conquest", "old_names": []}, {"date_last_updated": "2012-07-21 03:24:37", "id": 34181, "name": "Doctor Who: The Mazes of Time", "old_names": []}, {"date_last_updated": "2015-04-03 17:39:42", "id": 34182, "name": "The Testament of Sherlock Holmes", "old_names": []}, {"date_last_updated": "2011-02-17 13:58:42", "id": 34183, "name": "Laser War", "old_names": []}, {"date_last_updated": "2013-02-15 21:10:18", "id": 34184, "name": "Lethal Weapon 3", "old_names": []}, {"date_last_updated": "2015-05-06 20:00:20", "id": 34185, "name": "Phantom of the Opera", "old_names": []}, {"date_last_updated": "2011-02-17 22:05:22", "id": 34187, "name": "Bennu", "old_names": []}, {"date_last_updated": "2011-02-17 14:35:53", "id": 34188, "name": "Monday Night Football", "old_names": []}, {"date_last_updated": "2011-02-17 14:44:25", "id": 34189, "name": "Robocop", "old_names": []}, {"date_last_updated": "2011-05-23 13:02:28", "id": 34190, "name": "Space Shuttle", "old_names": []}, {"date_last_updated": "2011-02-17 15:06:53", "id": 34191, "name": "Time Machine", "old_names": []}, {"date_last_updated": "2012-07-16 02:29:44", "id": 34192, "name": "Teenage Mutant Ninja Turtles", "old_names": []}, {"date_last_updated": "2012-07-11 10:53:50", "id": 34193, "name": "Star Trek", "old_names": []}, {"date_last_updated": "2011-02-17 16:21:15", "id": 34194, "name": "The Who's Tommy: Pinball Wizard", "old_names": []}, {"date_last_updated": "2011-05-17 15:39:24", "id": 34195, "name": "Tales from the Crypt", "old_names": []}, {"date_last_updated": "2011-02-17 16:35:31", "id": 34196, "name": "Swords of Fury", "old_names": []}, {"date_last_updated": "2013-12-04 15:29:49", "id": 34197, "name": "Banzai Run", "old_names": []}, {"date_last_updated": "2011-05-22 23:03:58", "id": 34198, "name": "Big Guns", "old_names": []}, {"date_last_updated": "2015-09-26 21:28:45", "id": 34199, "name": "Black Knight 2000", "old_names": []}, {"date_last_updated": "2015-03-31 17:01:20", "id": 34200, "name": "The Blue Crystal Rod", "old_names": []}, {"date_last_updated": "2021-01-08 12:15:03", "id": 34201, "name": "AFL Live", "old_names": []}, {"date_last_updated": "2014-04-25 17:47:41", "id": 34202, "name": "Rio", "old_names": []}, {"date_last_updated": "2020-03-02 16:49:47", "id": 34203, "name": "Schwarzenberg", "old_names": []}, {"date_last_updated": "2012-05-16 17:25:36", "id": 34204, "name": "Transformers: Dark of the Moon", "old_names": []}, {"date_last_updated": "2017-06-26 13:57:21", "id": 34205, "name": "The Walking Dead", "old_names": []}, {"date_last_updated": "2011-02-18 09:18:02", "id": 34208, "name": "Wild Summer", "old_names": []}, {"date_last_updated": "2017-01-23 08:55:02", "id": 34209, "name": "Puzzle Agent 2", "old_names": []}, {"date_last_updated": "2019-11-13 13:42:00", "id": 34211, "name": "Hector: Badge of Carnage", "old_names": []}, {"date_last_updated": "2013-04-04 20:13:56", "id": 34212, "name": "King's Quest", "old_names": []}, {"date_last_updated": "2020-04-12 15:02:42", "id": 34213, "name": "The Wolf Among Us", "old_names": []}, {"date_last_updated": "2017-08-24 12:17:36", "id": 34214, "name": "Fit in Six", "old_names": []}, {"date_last_updated": "2011-03-06 17:03:57", "id": 34215, "name": "Mountain Maniac", "old_names": []}, {"date_last_updated": "2017-09-12 02:53:39", "id": 34216, "name": "Tom and Jerry: The Movie", "old_names": []}, {"date_last_updated": "2018-07-19 16:06:35", "id": 34217, "name": "The Blocks Cometh", "old_names": []}, {"date_last_updated": "2020-05-15 16:10:36", "id": 34218, "name": "Chaos Code", "old_names": []}, {"date_last_updated": "2014-06-03 15:34:28", "id": 34219, "name": "The Haunted: Hells Reach", "old_names": []}, {"date_last_updated": "2012-09-06 08:04:47", "id": 34220, "name": "Akai Katana Shin", "old_names": []}, {"date_last_updated": "2014-08-08 22:04:00", "id": 34221, "name": "Nin\u00b2 -Jump", "old_names": []}, {"date_last_updated": "2016-06-20 16:02:28", "id": 34222, "name": "Instant Brain", "old_names": []}, {"date_last_updated": "2014-06-28 14:06:37", "id": 34223, "name": "Inside a Star-filled Sky", "old_names": []}, {"date_last_updated": "2017-06-30 08:02:53", "id": 34224, "name": "Power Lode Runner", "old_names": []}, {"date_last_updated": "2019-06-08 12:48:39", "id": 34225, "name": "Asuka 120% Maxima Burning Fest.", "old_names": []}, {"date_last_updated": "2016-05-13 08:11:41", "id": 34226, "name": "Super Variable Geo", "old_names": []}, {"date_last_updated": "2018-01-18 00:44:59", "id": 34227, "name": "Goofy's Fun House", "old_names": []}, {"date_last_updated": "2011-02-21 11:22:26", "id": 34228, "name": "Office Disorders", "old_names": []}, {"date_last_updated": "2014-02-05 01:32:51", "id": 34229, "name": "Dungeon Raid", "old_names": []}, {"date_last_updated": "2015-08-26 02:17:32", "id": 34230, "name": "Coconuts", "old_names": []}, {"date_last_updated": "2018-06-07 16:37:09", "id": 34232, "name": "Burning Fists: Force Striker", "old_names": []}, {"date_last_updated": "2012-07-14 05:34:02", "id": 34233, "name": "SingStar Danske Hits", "old_names": []}, {"date_last_updated": "2011-02-21 10:00:17", "id": 34234, "name": "Club Caribe", "old_names": []}, {"date_last_updated": "2011-02-21 14:51:48", "id": 34235, "name": "Uo Poko", "old_names": []}, {"date_last_updated": "2016-12-07 14:06:43", "id": 34236, "name": "Mushihime-tama", "old_names": []}, {"date_last_updated": "2019-05-09 08:11:07", "id": 34237, "name": "Ketsui: Kizuna Jigoku Tachi", "old_names": []}, {"date_last_updated": "2014-08-22 01:03:08", "id": 34238, "name": "Deathsmiles IIX: Makai no Merry Christmas", "old_names": []}, {"date_last_updated": "2021-07-25 08:34:03", "id": 34239, "name": "Alternative World Games", "old_names": []}, {"date_last_updated": "2011-02-22 05:21:12", "id": 34242, "name": "Buku Dominoes", "old_names": []}, {"date_last_updated": "2011-02-22 06:51:31", "id": 34243, "name": "Taxi Racer GOLD", "old_names": []}, {"date_last_updated": "2016-04-05 16:25:33", "id": 34244, "name": "Asphalt 3D", "old_names": []}, {"date_last_updated": "2014-03-08 17:15:08", "id": 34245, "name": "Madden NFL Football", "old_names": []}, {"date_last_updated": "2018-05-16 00:36:14", "id": 34246, "name": "Eternal Legacy", "old_names": []}, {"date_last_updated": "2011-02-22 16:08:19", "id": 34247, "name": "Mushihime-sama Bug Panic", "old_names": []}]