[{"date_last_updated": "2014-01-27 11:38:18", "id": 24425, "name": "Rockman & Forte: Mirai kara no Chousensha"}, {"date_last_updated": "2015-09-27 18:01:36", "id": 24426, "name": "Ener-G Dance Squad"}, {"date_last_updated": "2008-11-10 15:33:17", "id": 24427, "name": "Ener-G Gym Rockets"}, {"date_last_updated": "2008-11-10 15:34:34", "id": 24428, "name": "Ener-G Horse Riders"}, {"date_last_updated": "2016-07-20 18:28:51", "id": 24429, "name": "The Hidden: Source"}, {"date_last_updated": "2017-05-30 21:23:30", "id": 24430, "name": "Bomberman Ultra"}, {"date_last_updated": "2009-09-17 10:55:10", "id": 24431, "name": "Rhiannon: Curse of the Four Branches"}, {"date_last_updated": "2010-02-20 18:14:55", "id": 24432, "name": "Petz Horse Club"}, {"date_last_updated": "2011-05-03 07:33:49", "id": 24433, "name": "Cesar Millan's Dog Whisperer"}, {"date_last_updated": "2020-03-29 15:41:24", "id": 24434, "name": "Powerslave"}, {"date_last_updated": "2008-11-17 18:14:13", "id": 24435, "name": "Ultimate Band"}, {"date_last_updated": "2008-11-10 23:54:05", "id": 24436, "name": "Double Teacher Life"}, {"date_last_updated": "2013-06-13 02:01:36", "id": 24437, "name": "Nami no Mani Mani - Sazanami Shinryoushou"}, {"date_last_updated": "2010-07-19 17:44:21", "id": 24439, "name": "Estamos Pensando"}, {"date_last_updated": "2012-03-09 16:52:36", "id": 24440, "name": "Major League Baseball 2K9"}, {"date_last_updated": "2008-11-11 16:38:44", "id": 24441, "name": "Venus Blood - Chimera -"}, {"date_last_updated": "2017-09-18 11:49:24", "id": 24442, "name": "NPPL Championship Paintball 2009"}, {"date_last_updated": "2012-08-04 15:10:23", "id": 24443, "name": "Madagascar: Operation Penguin"}, {"date_last_updated": "2011-05-27 17:37:43", "id": 24445, "name": "Supreme Commander 2"}, {"date_last_updated": "2008-11-12 16:57:13", "id": 24446, "name": "Asuka Josou Bishounen Choukyou Simulation"}, {"date_last_updated": "2013-08-12 14:25:42", "id": 24447, "name": "Bright Shadow"}, {"date_last_updated": "2009-05-17 07:00:34", "id": 24448, "name": "Luna Online"}, {"date_last_updated": "2012-06-23 08:04:02", "id": 24449, "name": "We Ski & Snowboard"}, {"date_last_updated": "2012-11-06 22:55:00", "id": 24450, "name": "Captain Planet and the Planeteers"}, {"date_last_updated": "2020-06-20 08:15:50", "id": 24451, "name": "Kingdom Under Fire II"}, {"date_last_updated": "2013-12-27 02:26:30", "id": 24452, "name": "Life of D. Duck II"}, {"date_last_updated": "2013-05-29 11:46:17", "id": 24453, "name": "Elona - Eternal League of Nefia"}, {"date_last_updated": "2017-04-18 04:28:35", "id": 24454, "name": "Super Batter Up"}, {"date_last_updated": "2008-11-14 11:42:58", "id": 24455, "name": "DSvision"}, {"date_last_updated": "2019-03-03 22:58:52", "id": 24456, "name": "Kingdom Under Fire: A War of Heroes"}, {"date_last_updated": "2008-11-28 12:17:23", "id": 24457, "name": "Pyroblazer"}, {"date_last_updated": "2012-07-19 13:28:20", "id": 24458, "name": "Tropico 3"}, {"date_last_updated": "2008-11-14 15:42:58", "id": 24465, "name": "Grow Island"}, {"date_last_updated": "2010-05-08 12:50:33", "id": 24466, "name": "Jagged Alliance"}, {"date_last_updated": "2008-11-17 13:35:29", "id": 24471, "name": "Nanatsuiro Drops"}, {"date_last_updated": "2014-05-04 19:00:46", "id": 24472, "name": "Shin Megami Tensei: Devil Survivor"}, {"date_last_updated": "2016-09-19 06:40:55", "id": 24473, "name": "CSI: NY"}, {"date_last_updated": "2017-03-07 20:48:08", "id": 24474, "name": "Wizards & Warriors Chapter X: The Fortress of Fear"}, {"date_last_updated": "2012-11-14 16:33:42", "id": 24476, "name": "Rapala Trophies"}, {"date_last_updated": "2008-11-16 14:10:22", "id": 24477, "name": "Rapala's Fishing Frenzy"}, {"date_last_updated": "2016-06-11 15:00:30", "id": 24478, "name": "Rapala Fishing Frenzy 2009"}, {"date_last_updated": "2014-06-17 13:08:04", "id": 24479, "name": "Blood of Bahamut"}, {"date_last_updated": "2008-11-16 11:25:59", "id": 24480, "name": "My Stop Smoking Coach with Allen Carr"}, {"date_last_updated": "2013-07-10 16:32:47", "id": 24481, "name": "EA Sports Active"}, {"date_last_updated": "2008-11-18 08:23:11", "id": 24482, "name": "Husky Express"}, {"date_last_updated": "2015-05-21 11:10:18", "id": 24483, "name": "Monkey Mischief! Party Time"}, {"date_last_updated": "2014-11-02 04:51:04", "id": 24485, "name": "Call of Duty: World at War Final Fronts"}, {"date_last_updated": "2013-12-28 02:27:58", "id": 24489, "name": "Imagine Party Babyz"}, {"date_last_updated": "2014-09-18 18:08:54", "id": 24490, "name": "Strong Bad's Cool Game for Attractive People Episode 5: 8-bit is Enough"}, {"date_last_updated": "2011-03-20 18:32:27", "id": 24491, "name": "Deer Drive"}, {"date_last_updated": "2018-03-02 07:20:09", "id": 24493, "name": "Bejeweled Twist"}, {"date_last_updated": "2012-08-04 15:33:52", "id": 24494, "name": "Bionicle: Maze of Shadows"}, {"date_last_updated": "2011-09-27 07:43:45", "id": 24495, "name": "Off-Road Redneck Racing"}, {"date_last_updated": "2008-11-19 20:58:02", "id": 24496, "name": "Mosby's Confederacy"}, {"date_last_updated": "2008-11-19 20:13:23", "id": 24497, "name": "Reconquista"}, {"date_last_updated": "2018-03-20 17:03:23", "id": 24498, "name": "In The Pit"}, {"date_last_updated": "2017-04-27 18:03:55", "id": 24499, "name": "Eragon"}, {"date_last_updated": "2008-11-20 03:35:19", "id": 24500, "name": "Eragon"}, {"date_last_updated": "2015-04-03 13:51:14", "id": 24502, "name": "Evasive Space"}, {"date_last_updated": "2018-05-24 18:19:47", "id": 24504, "name": "Beach de Reach"}, {"date_last_updated": "2017-12-30 05:51:38", "id": 24505, "name": "Hello Kitty Big City Dreams"}, {"date_last_updated": "2020-04-09 17:54:03", "id": 24506, "name": "Deal or No Deal: The Banker is Back"}, {"date_last_updated": "2016-08-23 06:56:00", "id": 24507, "name": "Pass the Pigs"}, {"date_last_updated": "2016-07-12 06:32:40", "id": 24509, "name": "Happy Happy Clover"}, {"date_last_updated": "2010-04-14 23:47:24", "id": 24510, "name": "Okada Toshio no Itsumade mo Debu to Omounayo"}, {"date_last_updated": "2009-08-10 08:11:24", "id": 24511, "name": "National Geographic Panda"}, {"date_last_updated": "2016-04-29 14:45:27", "id": 24512, "name": "Football Director DS"}, {"date_last_updated": "2018-01-15 21:19:28", "id": 24513, "name": "DiRT 2"}, {"date_last_updated": "2016-01-30 11:54:24", "id": 24514, "name": "Terminator Salvation"}, {"date_last_updated": "2012-03-29 09:55:51", "id": 24515, "name": "Ultimate Air Combat"}, {"date_last_updated": "2018-04-25 09:49:39", "id": 24516, "name": "Way of the Samurai 3"}, {"date_last_updated": "2017-12-25 19:07:44", "id": 24517, "name": "beatmania"}, {"date_last_updated": "2012-07-10 06:01:24", "id": 24518, "name": "beatmania 2ndMIX"}, {"date_last_updated": "2012-07-10 05:42:48", "id": 24519, "name": "beatmania 3rdMIX"}, {"date_last_updated": "2012-07-10 05:21:25", "id": 24520, "name": "beatmania 4thMIX ~the beat goes on~"}, {"date_last_updated": "2016-02-03 16:53:23", "id": 24522, "name": "Dominions: Priests, Prophets, and Pretenders"}, {"date_last_updated": "2017-08-26 21:25:27", "id": 24523, "name": "beatmania 5thMIX -Time to get down-"}, {"date_last_updated": "2018-01-07 13:46:02", "id": 24524, "name": "beatmania 6thMIX -THE UK UNDERGROUND MUSIC-"}]