[{"date_last_updated": "2017-09-27 18:42:29", "id": 61780, "name": "Kigurumi Kombat", "old_names": []}, {"date_last_updated": "2017-09-27 18:46:26", "id": 61781, "name": "Tales of Lunea", "old_names": []}, {"date_last_updated": "2017-09-27 19:36:32", "id": 61782, "name": "Zoo Tycoon: Ultimate Animal Collection", "old_names": []}, {"date_last_updated": "2017-10-07 04:04:41", "id": 61783, "name": "Blocky Roads", "old_names": []}, {"date_last_updated": "2017-09-27 23:59:17", "id": 61784, "name": "Cat Simulator", "old_names": []}, {"date_last_updated": "2017-09-28 00:03:04", "id": 61785, "name": "Buttons and Scissors", "old_names": []}, {"date_last_updated": "2017-09-28 00:06:28", "id": 61786, "name": "Car Race", "old_names": []}, {"date_last_updated": "2020-07-07 13:58:45", "id": 61787, "name": "Blox", "old_names": []}, {"date_last_updated": "2017-09-28 00:12:11", "id": 61788, "name": "Color Oil", "old_names": []}, {"date_last_updated": "2017-09-28 00:15:00", "id": 61789, "name": "Crash it Smash it", "old_names": []}, {"date_last_updated": "2017-09-28 01:00:39", "id": 61790, "name": "Garage Escape", "old_names": []}, {"date_last_updated": "2017-09-28 01:06:24", "id": 61791, "name": "Flip Boarder \u2013 Touch Snowboard", "old_names": []}, {"date_last_updated": "2017-09-28 01:13:48", "id": 61792, "name": "Hidden Objects Thanksgiving & 3 puzzle games", "old_names": []}, {"date_last_updated": "2018-02-03 08:14:12", "id": 61793, "name": "How The Grinch Stole Christmas! - Dr. Seuss", "old_names": []}, {"date_last_updated": "2017-09-28 04:23:29", "id": 61794, "name": "Mind Games", "old_names": []}, {"date_last_updated": "2020-07-10 10:35:50", "id": 61795, "name": "Starfall Numbers", "old_names": []}, {"date_last_updated": "2017-09-28 01:54:11", "id": 61796, "name": "Toca Pet Doctor", "old_names": []}, {"date_last_updated": "2017-09-28 01:53:48", "id": 61797, "name": "Toca Life: Town", "old_names": []}, {"date_last_updated": "2017-09-28 01:53:24", "id": 61798, "name": "Toca Lab: Elements", "old_names": []}, {"date_last_updated": "2021-08-09 18:08:52", "id": 61799, "name": "Home Sweet Home", "old_names": []}, {"date_last_updated": "2017-09-29 08:30:48", "id": 61800, "name": "Shuffle Board", "old_names": []}, {"date_last_updated": "2019-03-27 10:35:06", "id": 61801, "name": "Major Maox", "old_names": []}, {"date_last_updated": "2019-03-27 11:10:36", "id": 61802, "name": "Killing Moon", "old_names": []}, {"date_last_updated": "2019-09-09 06:46:15", "id": 61803, "name": "Pocket Professor: KwikNotes Volume One", "old_names": []}, {"date_last_updated": "2017-09-29 12:49:42", "id": 61804, "name": "Okriinu", "old_names": []}, {"date_last_updated": "2017-09-29 13:22:26", "id": 61805, "name": "Tunnels of Fahad ", "old_names": []}, {"date_last_updated": "2019-10-18 19:51:04", "id": 61806, "name": "Earth Defense Force: Iron Rain", "old_names": []}, {"date_last_updated": "2018-04-30 13:13:23", "id": 61807, "name": "Earth Defense Force 4.1: Wing Diver The Shooter", "old_names": []}, {"date_last_updated": "2017-09-29 21:21:39", "id": 61808, "name": "Dark Lord", "old_names": []}, {"date_last_updated": "2018-04-28 11:44:17", "id": 61809, "name": "Kimi wa Hero ~ Taiketsu!", "old_names": []}, {"date_last_updated": "2017-11-16 08:23:38", "id": 61810, "name": "Party Planet", "old_names": []}, {"date_last_updated": "2018-03-11 22:43:03", "id": 61811, "name": "Reel Fishing: The Great Outdoors", "old_names": []}, {"date_last_updated": "2017-09-30 05:24:43", "id": 61812, "name": "Skadonk Showdown", "old_names": []}, {"date_last_updated": "2017-09-30 05:45:00", "id": 61863, "name": "The Afterwoods", "old_names": []}, {"date_last_updated": "2017-10-01 09:11:28", "id": 61864, "name": "Caligo", "old_names": []}, {"date_last_updated": "2020-08-17 23:34:20", "id": 61865, "name": "Vaporum", "old_names": []}, {"date_last_updated": "2017-09-30 05:48:17", "id": 61866, "name": "Kharon's Crypt", "old_names": []}, {"date_last_updated": "2017-09-30 11:59:30", "id": 61867, "name": "Zeiramzone", "old_names": []}, {"date_last_updated": "2017-09-30 12:01:59", "id": 61868, "name": "Zig Zag Ball", "old_names": []}, {"date_last_updated": "2017-09-30 05:50:28", "id": 61869, "name": "A Near Dawn", "old_names": []}, {"date_last_updated": "2017-09-30 05:51:18", "id": 61870, "name": "Restless World", "old_names": []}, {"date_last_updated": "2018-12-29 17:23:30", "id": 61871, "name": "Cloudborn", "old_names": []}, {"date_last_updated": "2019-08-14 19:15:26", "id": 61872, "name": "Ancestors Legacy", "old_names": []}, {"date_last_updated": "2018-02-01 07:28:40", "id": 61873, "name": "Stick Fight: The Game", "old_names": []}, {"date_last_updated": "2017-09-30 06:02:43", "id": 61874, "name": "Duel of Summoners: The Mabinogi Card Game", "old_names": []}, {"date_last_updated": "2019-07-05 11:02:00", "id": 61875, "name": "Yet Another Zombie Defense HD", "old_names": []}, {"date_last_updated": "2021-02-06 14:33:08", "id": 61876, "name": "Fall of Light", "old_names": []}, {"date_last_updated": "2017-10-16 16:07:21", "id": 61877, "name": "Schlag den Star", "old_names": []}, {"date_last_updated": "2018-07-20 16:07:55", "id": 61878, "name": "Urban Pirate", "old_names": []}, {"date_last_updated": "2017-09-30 06:23:24", "id": 61879, "name": "Digital Master", "old_names": []}]