[{"date_last_updated": "2021-02-24 13:14:37", "id": 26026, "name": "Koi Koi Mahjong", "old_names": []}, {"date_last_updated": "2021-02-24 15:07:34", "id": 26027, "name": "Syougi no Tatsujin", "old_names": []}, {"date_last_updated": "2009-04-26 14:31:18", "id": 26028, "name": "Melon Chan's Growth Diary", "old_names": []}, {"date_last_updated": "2013-08-26 10:47:41", "id": 26029, "name": "Memories Off: Pure", "old_names": []}, {"date_last_updated": "2009-04-26 14:41:24", "id": 26030, "name": "Mezase! Kanji Ou", "old_names": []}, {"date_last_updated": "2009-04-26 18:19:01", "id": 26031, "name": "Neo Baccarat", "old_names": []}, {"date_last_updated": "2009-08-18 17:32:34", "id": 26032, "name": "Million KNights Vermilion", "old_names": []}, {"date_last_updated": "2009-04-26 20:35:19", "id": 26033, "name": "Remington Big Buck Trophy Hunt", "old_names": []}, {"date_last_updated": "2021-06-23 11:01:24", "id": 26034, "name": "Tenchi no Mon 2: Busouden", "old_names": []}, {"date_last_updated": "2009-04-26 20:51:45", "id": 26035, "name": "Ultimate Civil War Battles: Robert E. Lee vs. Ulysses S. Grant", "old_names": []}, {"date_last_updated": "2010-10-24 12:52:06", "id": 26036, "name": "Divus Rabies", "old_names": []}, {"date_last_updated": "2009-04-26 22:39:54", "id": 26037, "name": "Smashing Toys", "old_names": []}, {"date_last_updated": "2009-04-27 03:13:44", "id": 26038, "name": "Valkyrie Complex", "old_names": []}, {"date_last_updated": "2014-01-27 12:55:24", "id": 26039, "name": "Doala de Wii", "old_names": []}, {"date_last_updated": "2019-06-15 10:01:21", "id": 26040, "name": "Akira", "old_names": []}, {"date_last_updated": "2017-09-18 11:57:39", "id": 26041, "name": "Alfred Chicken", "old_names": []}, {"date_last_updated": "2017-12-11 11:51:30", "id": 26042, "name": "Holy Diver", "old_names": []}, {"date_last_updated": "2017-06-03 03:19:50", "id": 26043, "name": "Midnight Race Club: Supercharged!", "old_names": []}, {"date_last_updated": "2011-06-04 15:22:05", "id": 26044, "name": "Mr. T", "old_names": []}, {"date_last_updated": "2009-04-27 13:10:18", "id": 26045, "name": "Witch's Workshop", "old_names": []}, {"date_last_updated": "2009-04-27 13:48:12", "id": 26046, "name": "CrocPond", "old_names": []}, {"date_last_updated": "2009-04-27 15:43:30", "id": 26047, "name": "Aya Go", "old_names": []}, {"date_last_updated": "2015-12-19 20:58:38", "id": 26048, "name": "Rocky", "old_names": []}, {"date_last_updated": "2018-07-21 17:40:48", "id": 26049, "name": "Sakura Sakura", "old_names": []}, {"date_last_updated": "2012-07-21 04:57:50", "id": 26050, "name": "Dora the Explorer Wildlife Rescue", "old_names": []}, {"date_last_updated": "2020-07-06 17:20:02", "id": 26051, "name": "Letters on the Loose", "old_names": []}, {"date_last_updated": "2012-11-23 08:23:58", "id": 26052, "name": "Disney Princess Enchanted Learning", "old_names": []}, {"date_last_updated": "2009-04-28 14:50:51", "id": 26053, "name": "1st Grade", "old_names": []}, {"date_last_updated": "2012-07-06 07:56:02", "id": 26054, "name": "Cars", "old_names": []}, {"date_last_updated": "2012-07-06 07:49:46", "id": 26055, "name": "Cars Supercharged", "old_names": []}, {"date_last_updated": "2014-12-13 20:46:16", "id": 26056, "name": "Cosmic Math", "old_names": []}, {"date_last_updated": "2012-11-23 08:34:35", "id": 26057, "name": "Disney Princess Worlds of Enchantment", "old_names": []}, {"date_last_updated": "2012-07-21 04:59:57", "id": 26058, "name": "Dora the Explorer", "old_names": []}, {"date_last_updated": "2018-06-27 21:29:51", "id": 26059, "name": "Finding Nemo", "old_names": []}, {"date_last_updated": "2012-05-10 23:36:33", "id": 26060, "name": "Foster's Home for Imaginary Friends", "old_names": []}, {"date_last_updated": "2012-07-21 04:59:48", "id": 26061, "name": "Go Diego Go! Animal Rescuer", "old_names": []}, {"date_last_updated": "2009-04-28 14:55:26", "id": 26062, "name": "Kindergarten", "old_names": []}, {"date_last_updated": "2018-06-27 14:19:18", "id": 26063, "name": "Mr. Pencil's Learn to Draw and Write", "old_names": []}, {"date_last_updated": "2020-05-28 03:10:24", "id": 26064, "name": "Pet Pals", "old_names": []}, {"date_last_updated": "2012-07-06 07:50:18", "id": 26065, "name": "Ratatouille", "old_names": []}, {"date_last_updated": "2009-04-28 15:04:54", "id": 26066, "name": "Scholastic Animal Genius", "old_names": []}, {"date_last_updated": "2017-06-17 15:21:45", "id": 26067, "name": "Scholastic: Clifford The Big Red Dog - Reading", "old_names": []}, {"date_last_updated": "2009-04-28 15:05:34", "id": 26068, "name": "Scholastic Get Puzzled", "old_names": []}, {"date_last_updated": "2019-07-01 10:24:45", "id": 26069, "name": "Sonic X", "old_names": []}, {"date_last_updated": "2018-06-27 14:20:40", "id": 26070, "name": "SpongeBob SquarePants", "old_names": []}, {"date_last_updated": "2014-01-27 12:54:29", "id": 26071, "name": "The Backyardigans", "old_names": []}, {"date_last_updated": "2012-07-11 08:37:29", "id": 26072, "name": "The Batman", "old_names": []}, {"date_last_updated": "2012-11-23 08:17:05", "id": 26073, "name": "The Batman Strength in Numbers", "old_names": []}, {"date_last_updated": "2012-11-23 08:28:09", "id": 26074, "name": "The Incredibles", "old_names": []}, {"date_last_updated": "2012-06-17 06:34:36", "id": 26075, "name": "Thomas and Friends: Calling All Engines", "old_names": []}, {"date_last_updated": "2012-07-21 04:59:42", "id": 26076, "name": "Dora's Camping Adventure", "old_names": []}, {"date_last_updated": "2018-06-27 21:31:40", "id": 26077, "name": "Creature Create", "old_names": []}, {"date_last_updated": "2009-04-28 15:09:33", "id": 26078, "name": "Scholastic I Spy", "old_names": []}, {"date_last_updated": "2014-01-25 18:29:12", "id": 26079, "name": "Scholastic Math Missions", "old_names": []}, {"date_last_updated": "2018-04-15 12:08:13", "id": 26080, "name": "I Spy Treasure Hunt", "old_names": []}, {"date_last_updated": "2018-06-27 21:27:25", "id": 26081, "name": "Outwit!", "old_names": []}, {"date_last_updated": "2020-08-12 16:19:15", "id": 26082, "name": "Wall-E", "old_names": []}, {"date_last_updated": "2012-07-10 09:40:29", "id": 26083, "name": "Star Wars: Jedi Reading", "old_names": []}, {"date_last_updated": "2012-07-10 08:46:31", "id": 26084, "name": "Star Wars: Jedi Math", "old_names": []}, {"date_last_updated": "2015-02-14 12:20:46", "id": 26085, "name": "MySims Agents", "old_names": []}, {"date_last_updated": "2013-03-03 18:41:31", "id": 26087, "name": "Mass Effect: Galaxy", "old_names": []}, {"date_last_updated": "2014-02-27 19:21:18", "id": 26088, "name": "Soulcalibur: Broken Destiny", "old_names": []}, {"date_last_updated": "2011-02-21 10:28:53", "id": 26089, "name": "Brain Exercise with Dr. Kawashima", "old_names": []}, {"date_last_updated": "2019-07-17 18:20:59", "id": 26092, "name": "Rad Mobile", "old_names": []}, {"date_last_updated": "2009-04-29 05:55:52", "id": 26093, "name": "Big Event Golf", "old_names": []}, {"date_last_updated": "2022-09-13 15:11:52", "id": 26094, "name": "Wacky World of Sports", "old_names": []}, {"date_last_updated": "2016-03-15 04:49:35", "id": 26095, "name": "Tom Clancy's Ghost Recon: Future Soldier", "old_names": []}, {"date_last_updated": "2009-04-29 15:04:17", "id": 26096, "name": "Reincarnation Shinsengumi!", "old_names": []}, {"date_last_updated": "2018-05-08 06:40:45", "id": 26097, "name": "Killing Floor", "old_names": []}, {"date_last_updated": "2009-04-29 13:36:56", "id": 26098, "name": "Apollo 13", "old_names": []}, {"date_last_updated": "2009-04-29 13:41:32", "id": 26099, "name": "Daytona Racing", "old_names": []}, {"date_last_updated": "2014-10-02 01:45:49", "id": 26100, "name": "Thayer's Quest", "old_names": []}, {"date_last_updated": "2017-03-09 00:10:00", "id": 26101, "name": "PixelJunk Shooter", "old_names": []}, {"date_last_updated": "2013-02-01 15:03:01", "id": 26102, "name": "Sled Shred featuring the Jamaican Bobsled Team", "old_names": []}, {"date_last_updated": "2017-12-10 14:46:31", "id": 26104, "name": "Hana to Otome ni Shukufuku wo", "old_names": []}, {"date_last_updated": "2014-08-21 15:04:46", "id": 26105, "name": "The King of Fighters Online", "old_names": []}, {"date_last_updated": "2014-03-04 15:33:35", "id": 26106, "name": "Sakutsuku DS: Touch and Direct", "old_names": []}, {"date_last_updated": "2009-04-30 12:11:59", "id": 26108, "name": "20th Century Video Almanac", "old_names": []}, {"date_last_updated": "2009-04-30 12:09:58", "id": 26109, "name": "3D Atlas", "old_names": []}, {"date_last_updated": "2013-11-05 00:25:45", "id": 26110, "name": "Adventures of Pinocchio", "old_names": []}, {"date_last_updated": "2015-09-29 11:55:24", "id": 26111, "name": "Cinderella's Fairy Tale", "old_names": []}, {"date_last_updated": "2020-06-18 05:16:29", "id": 26112, "name": "Advanced Dungeons & Dragons: Slayer", "old_names": []}, {"date_last_updated": "2012-10-19 12:39:11", "id": 26113, "name": "Dalmatians 4", "old_names": []}, {"date_last_updated": "2010-04-28 20:31:26", "id": 26114, "name": "Hoppie II", "old_names": []}, {"date_last_updated": "2010-05-20 23:25:30", "id": 26115, "name": "Monster Eggs II", "old_names": []}, {"date_last_updated": "2013-12-17 12:51:37", "id": 26116, "name": "Peter Pan's Playground", "old_names": []}, {"date_last_updated": "2009-04-30 13:50:13", "id": 26117, "name": "Princess Snow White", "old_names": []}, {"date_last_updated": "2019-01-09 10:29:09", "id": 26118, "name": "A Week of Garfield", "old_names": []}, {"date_last_updated": "2014-09-04 10:55:05", "id": 26119, "name": "S.T.A.L.K.E.R.: Call of Pripyat", "old_names": []}, {"date_last_updated": "2015-11-14 11:03:08", "id": 26120, "name": "Neo Cherry Master Color", "old_names": []}, {"date_last_updated": "2019-04-26 14:46:04", "id": 26121, "name": "Buzz: Brain of Oz", "old_names": []}, {"date_last_updated": "2017-11-12 20:20:38", "id": 26122, "name": "Mobile Suit Gundam: Encounters in Space", "old_names": []}, {"date_last_updated": "2014-03-06 14:42:05", "id": 26123, "name": "PDC World Championship Darts", "old_names": []}, {"date_last_updated": "2014-01-30 15:10:55", "id": 26124, "name": "Petanque Pro", "old_names": []}, {"date_last_updated": "2020-06-19 05:35:47", "id": 26125, "name": "The Ultimate Trivia Quiz", "old_names": []}]